README
setup.py
picplz/__init__.py
picplz/api.py
picplz/authentication.py
picplz/errors.py
picplz/helpers.py
picplz/local_settings.py
picplz/objects.py
picplz/tests.py
picplz/utils.py
python_picplz.egg-info/PKG-INFO
python_picplz.egg-info/SOURCES.txt
python_picplz.egg-info/dependency_links.txt
python_picplz.egg-info/top_level.txt
python_picplz.egg-info/zip-safe