Metadata-Version: 1.0
Name: python-picplz
Version: 0.2
Summary: Picplz library for Python
Home-page: http://github.com/ejesse/python-picplz
Author: Jesse Emery
Author-email: jesse@onagertech.com
License: MIT
Keywords: picplz library
Platform: UNKNOWN
